<annotation>
	<folder>train</folder>
	<filename>img006719.jpg</filename>
	<path>C:\Users\jacob\Documents\Projects\CSGO_Train\images\train\img006719.jpg</path>
	<source>
		<database>Unknown</database>
	</source>
	<size>
		<width>600</width>
		<height>600</height>
		<depth>3</depth>
	</size>
	<segmented>0</segmented>
	<object>
		<name>ct_body</name>
		<pose>Unspecified</pose>
		<truncated>0</truncated>
		<difficult>0</difficult>
		<bndbox>
			<xmin>290</xmin>
			<ymin>222</ymin>
			<xmax>334</xmax>
			<ymax>290</ymax>
		</bndbox>
	</object>
	<object>
		<name>ct_head</name>
		<pose>Unspecified</pose>
		<truncated>0</truncated>
		<difficult>0</difficult>
		<bndbox>
			<xmin>298</xmin>
			<ymin>222</ymin>
			<xmax>320</xmax>
			<ymax>244</ymax>
		</bndbox>
	</object>
</annotation>
